odata1c/odata1c.py
odata1c/odata1cparser.py
odata1c/__init__.py
odata1c-0.0.2.dist-info/RECORD
odata1c-0.0.2.dist-info/pbr.json
odata1c-0.0.2.dist-info/entry_points.txt
odata1c-0.0.2.dist-info/METADATA
odata1c-0.0.2.dist-info/WHEEL
odata1c-0.0.2.dist-info/DESCRIPTION.rst
odata1c-0.0.2.dist-info/top_level.txt
odata1c-0.0.2.dist-info/metadata.json
