Metadata-Version: 2.0
Name: odata1c
Version: 0.0.2
Summary: OData 1C API
Home-page: https://github.com/surge-/1c_odata_python
Author: Sergey Bryukov
Author-email: sbryukov@gmail.com
License: MIT
Keywords: 1C development
Platform: UNKNOWN
Classifier: Development Status :: 3 - Alpha
Classifier: Intended Audience :: Developers
Classifier: Topic :: Software Development :: Build Tools
Classifier: License :: OSI Approved :: MIT License
Classifier: Programming Language :: Python :: 2
Classifier: Programming Language :: Python :: 2.6
Classifier: Programming Language :: Python :: 2.7
Classifier: Programming Language :: Python :: 3
Classifier: Programming Language :: Python :: 3.2
Classifier: Programming Language :: Python :: 3.3
Classifier: Programming Language :: Python :: 3.4
Requires-Dist: urllib2
Requires-Dist: requests
Requires-Dist: lxml
Provides-Extra: dev
Requires-Dist: check-manifest; extra == 'dev'
Provides-Extra: test
Requires-Dist: coverage; extra == 'test'
